{
	"place_id": 298085623,
	"licence": "Data © OpenStreetMap contributors, ODbL 1.0. http://osm.org/copyright",
	"osm_type": "way",
	"osm_id": 123456789,
	"lat": "38.6270025",
	"lon": "-90.1994042",
	"category": "building",
	"type": "yes",
	"place_rank": 30,
	"importance": 0.00000999999999995449,
	"addresstype": "building",
	"name": "",
	"display_name": "100 Market Street, St. Louis, St. Louis City, Missouri, 63101, United States",
	"address": {
		"house_number": "100",
		"road": "Market Street",
		"city": "St. Louis",
		"county": "St. Louis City",
		"state": "Missouri",
		"ISO3166-2-lvl4": "US-MO",
		"postcode": "63101",
		"country": "United States",
		"country_code": "us"
	},
	"boundingbox": ["38.6268525", "38.6271525", "-90.1996542", "-90.1991542"]
}
